smartcase/__init__.py
smartcase/cleaner.py
smartcase-0.1.0.dist-info/METADATA
smartcase-0.1.0.dist-info/WHEEL
smartcase-0.1.0.dist-info/top_level.txt
smartcase-0.1.0.dist-info/RECORD
