Metadata-Version: 2.1
Name: smartcase
Version: 0.1.0
Summary: A smart text cleaner that preserves important capitalization using NER
Home-page: https://github.com/Nivetha9april/smartcase.git
Author: Nivetha G
Author-email: your.email@example.com
Requires-Python: >=3.6
Requires-Dist: spacy
